LICENSE
MANIFEST.in
README.md
setup.cfg
setup.py
version.py
bin/ioteclabs_credentials
ioteclabs_wrapper/__init__.py
ioteclabs_wrapper.egg-info/PKG-INFO
ioteclabs_wrapper.egg-info/SOURCES.txt
ioteclabs_wrapper.egg-info/dependency_links.txt
ioteclabs_wrapper.egg-info/requires.txt
ioteclabs_wrapper.egg-info/top_level.txt
ioteclabs_wrapper/core/__init__.py
ioteclabs_wrapper/core/access.py
ioteclabs_wrapper/core/base_classes.py
ioteclabs_wrapper/core/exceptions.py
ioteclabs_wrapper/credentials/__init__.py
ioteclabs_wrapper/credentials/credential_manager.py
ioteclabs_wrapper/modules/__init__.py
ioteclabs_wrapper/modules/account.py
ioteclabs_wrapper/modules/admin.py
ioteclabs_wrapper/modules/beeswax.py
ioteclabs_wrapper/modules/right_person.py
ioteclabs_wrapper/modules/user.py
ioteclabs_wrapper/modules/xcm.py