Metadata-Version: 1.1
Name: ioteclabs-wrapper
Version: 1.0.2
Summary: Python Wrapper for the iotec labs API
Home-page: https://github.com/iotgdev/ioteclabs-wrapper/
Author: iotec
Author-email: dev@dsp.io
License: MIT
Download-URL: https://github.com/iotgdev/ioteclabs-wrapper/archive/1.0.2.tar.gz
Platform: Development Status :: 5 - Production/Stable
Platform: Intended Audience :: Developers
Platform: License :: OSI Approved :: MIT License
Platform: Natural Language :: English
Platform: Operating System :: POSIX :: Linux
Platform: Programming Language :: Python :: 2
Platform: Programming Language :: Python :: 3
